{
  "db_name": "PostgreSQL",
  "query": "SELECT id, name, version FROM packages WHERE id = $1",
  "describe": {
    "columns": [
      {
        "ordinal": 0,
        "name": "id",
        "type_info": "Uuid"
      },
      {
        "ordinal": 1,
        "name": "name",
        "type_info": "Varchar"
      },
      {
        "ordinal": 2,
        "name": "version",
        "type_info": "Varchar"
      }
    ],
    "parameters": {
      "Left": [
        "Uuid"
      ]
    },
    "nullable": [
      false,
      false,
      false
    ]
  },
  "hash": "b9bb80ebf44b9f043a1be73a97816d4038d301ce140dc245e002397ef2bdc11f"
}
